GROGU1/GROGU_electronic.py
GROGU1/GROGU_finance.py
GROGU1/GROGU_food.py
GROGU1/GROGU_hotel.py
GROGU1/GROGU_lexicon_electronic.txt
GROGU1/GROGU_lexicon_finance.txt
GROGU1/GROGU_lexicon_food.txt
GROGU1/GROGU_lexicon_hotel.txt
GROGU1/__init__.py
GROGU1/emoji_utf8_lexicon.txt
GROGU1-1.1.dist-info/LICENSE.txt
GROGU1-1.1.dist-info/METADATA
GROGU1-1.1.dist-info/WHEEL
GROGU1-1.1.dist-info/top_level.txt
GROGU1-1.1.dist-info/RECORD
