Metadata-Version: 2.1
Name: GROGU1
Version: 1.1
Summary: Pacchetto contentente 4 dizionari che fungono da miglioramento di Vader per argomanti specifici, quali recensioni di cibi, finanza, recensioni Disneyland e recensioni di prodotti elettronici. Il pacchetto è creato a partire da quello cjhutto (https://github.com/cjhutto/vaderSentiment)
Home-page: https://github.com/Grogu0/GROGU
Author: ['GROGU']
Author-email: groguvsvader@gmail.com
License: MIT License: http://opensource.org/licenses/MIT
Keywords: grogu,vader,sentiment,analysis,opinion,mining,nlp,text,data,text analysis,opinion analysis,sentiment analysis,text mining,twitter sentiment,opinion mining,social media,twitter,social,media
Platform: any
Classifier: Development Status :: 4 - Beta
Classifier: Intended Audience :: Science/Research
Classifier: License :: OSI Approved :: MIT License
Classifier: Natural Language :: English
Classifier: Programming Language :: Python :: 3.5
Classifier: Topic :: Scientific/Engineering :: Artificial Intelligence
Classifier: Topic :: Scientific/Engineering :: Information Analysis
Classifier: Topic :: Text Processing :: Linguistic
Classifier: Topic :: Text Processing :: General
License-File: LICENSE.txt
Requires-Dist: requests
